LICENSE.md
wpilib_ws/__init__.py
wpilib_ws/hardware.py
wpilib_ws/server.py
wpilib_ws/utils.py
wpilib_ws_py-0.3.0.dist-info/LICENSE.md
wpilib_ws_py-0.3.0.dist-info/WHEEL
wpilib_ws_py-0.3.0.dist-info/METADATA
wpilib_ws_py-0.3.0.dist-info/RECORD
