Metadata-Version: 2.1
Name: wpilib-ws-py
Version: 0.3.0
Summary: An implementation of the WPILib WebSocket protocol for Python
Home-page: https://github.com/AM2i9/wpilib-ws-py
License: MIT
Keywords: wpilib,websocket
Author: Patrick Brennan (AM2i9)
Requires-Python: >=3.9,<4.0
Classifier: License :: OSI Approved :: MIT License
Classifier: Programming Language :: Python :: 3
Classifier: Programming Language :: Python :: 3.10
Classifier: Programming Language :: Python :: 3.9
Requires-Dist: websockets (>=10.0,<11.0)
Project-URL: Repository, https://github.com/AM2i9/wpilib-ws-py
